CHANGELOG.md
CODE_OF_CONDUCT.md
CONTRIBUTING.md
LICENSE
MANIFEST.in
Makefile
README.md
pyproject.toml
requirements.txt
setup.cfg
setup.py
docs/flashy/adversarial.html
docs/flashy/distrib.html
docs/flashy/formatter.html
docs/flashy/index.html
docs/flashy/logging.html
docs/flashy/solver.html
docs/flashy/state.html
docs/flashy/utils.html
docs/flashy/loggers/base.html
docs/flashy/loggers/index.html
docs/flashy/loggers/localfs.html
docs/flashy/loggers/tensorboard.html
docs/flashy/loggers/utils.html
docs/flashy/loggers/wandb.html
examples/basic/__init__.py
examples/basic/train.py
examples/basic/config/config.yaml
examples/cifar/__init__.py
examples/cifar/solver.py
examples/cifar/train.py
examples/cifar/config/config.yaml
flashy/__init__.py
flashy/adversarial.py
flashy/distrib.py
flashy/formatter.py
flashy/logging.py
flashy/py.typed
flashy/solver.py
flashy/state.py
flashy/utils.py
flashy.egg-info/PKG-INFO
flashy.egg-info/SOURCES.txt
flashy.egg-info/dependency_links.txt
flashy.egg-info/requires.txt
flashy.egg-info/top_level.txt
flashy/loggers/__init__.py
flashy/loggers/base.py
flashy/loggers/localfs.py
flashy/loggers/tensorboard.py
flashy/loggers/utils.py
flashy/loggers/wandb.py
tests/__init__.py
tests/test_distrib.py
tests/test_formatter.py
tests/test_integ.py
tests/test_solver.py
tests/test_state.py
tests/dummy/__init__.py
tests/dummy/train.py