Metadata-Version: 2.1
Name: flashy
Version: 0.0.2
Summary: Minimal solver for deep learning
Home-page: https://github.com/fairinternal/flashy
Author: Alexandre Défossez
Author-email: defossez@fb.com
License: MIT
Platform: UNKNOWN
Classifier: License :: OSI Approved :: MIT License
Classifier: Topic :: Scientific/Engineering :: Artificial Intelligence
Requires-Python: >=3.8.0
Provides-Extra: dev
